drumpler/__init__.py
drumpler/__version__.py
drumpler/drumpler.py
drumpler/sql_base.py
drumpler/sql_event.py
drumpler/sql_job.py
drumpler/sql_request.py
Drumpler-2.2.10.dist-info/LICENSE
Drumpler-2.2.10.dist-info/METADATA
Drumpler-2.2.10.dist-info/WHEEL
Drumpler-2.2.10.dist-info/top_level.txt
Drumpler-2.2.10.dist-info/RECORD
