Metadata-Version: 2.1
Name: Drumpler
Version: 2.2.10
Summary: Framework for rapidly developing a restful API that requires post processing
Home-page: https://github.com/KarelOmab/Drumpler
Author: Karel Tutsu
Author-email: karel.tutsu@gmail.com
Classifier: Programming Language :: Python :: 3
Classifier: License :: OSI Approved :: MIT License
Classifier: Operating System :: OS Independent
Requires-Python: >=3.6
License-File: LICENSE
Requires-Dist: Flask
Requires-Dist: python-dotenv
Requires-Dist: SQLAlchemy
Requires-Dist: Flask-SQLAlchemy
Requires-Dist: psycopg2-binary
Requires-Dist: psutil
